august-2.4.0.dist-info/METADATA
august-2.4.0.dist-info/WHEEL
august.cpython-35m-x86_64-linux-gnu.so
august-2.4.0.dist-info/RECORD
