Metadata-Version: 2.1
Name: august
Version: 2.4.0
Summary: A library for converting HTML to plain text.
Keywords: text html converter email
Home-Page: https://gitlab.com/alantrick/august/
Author: Alan Trick <me@alantrick.ca>
Author-Email: Alan Trick <me@alantrick.ca>
License: LGPL-3.0-or-later
